{"2.8.4-0": ["Sat Nov 26 2016", "Orocos Developers", "orocos-dev@lists.mech.kuleuven.be"], "2.8.2-0": ["Mon Dec 21 2015", "Orocos Developers", "orocos-dev@lists.mech.kuleuven.be"], "2.8.0-0": ["Fri Jan 23 2015", "OCL Development Team", "orocos-dev@lists.mech.kuleuven.be"], "2.8.0-1": ["Tue May 05 2015", "Orocos Developers", "orocos-dev@lists.mech.kuleuven.be"], "2.8.1-0": ["Tue Jul 21 2015", "Orocos Developers", "orocos-dev@lists.mech.kuleuven.be"], "2.8.3-1": ["Thu Sep 08 2016", "Orocos Developers", "orocos-dev@lists.mech.kuleuven.be"], "2.8.3-0": ["Thu Aug 11 2016", "Orocos Developers", "orocos-dev@lists.mech.kuleuven.be"]}